LICENSE.txt
README.md
setup.py
peekpoke/__init__.py
peekpoke.egg-info/PKG-INFO
peekpoke.egg-info/SOURCES.txt
peekpoke.egg-info/dependency_links.txt
peekpoke.egg-info/requires.txt
peekpoke.egg-info/top_level.txt