Metadata-Version: 2.1
Name: peekpoke
Version: 0.6.3
Summary: Remote hub memory tool for the Propeller microcontroller.
Home-page: http://siedell.com/projects/PeekPoke
Author: Chris Siedell
Author-email: chris@siedell.com
License: MIT
Project-URL: Python Documentation, https://github.com/chris-siedell/PeekPoke/wiki/PeekPoke-Python-Documentation
Project-URL: Spin Documentation, https://github.com/chris-siedell/PeekPoke/wiki/PeekPoke-Spin-Documentation
Project-URL: Source, https://github.com/chris-siedell/PeekPoke
Project-URL: Homepage, http://siedell.com/projects/PeekPoke
Keywords: Parallax Propeller P8X32A
Platform: UNKNOWN
Classifier: Development Status :: 3 - Alpha
Classifier: License :: OSI Approved :: MIT License
Classifier: Programming Language :: Python :: 3
Requires-Python: >=3
